{
	"name": "CopyPipeline_93f",
	"properties": {
		"activities": [
			{
				"name": "Copy_93f",
				"type": "Copy",
				"dependsOn": [],
				"policy": {
					"timeout": "7.00:00:00",
					"retry": 0,
					"retryIntervalInSeconds": 30,
					"secureOutput": false,
					"secureInput": false
				},
				"userProperties": [
					{
						"name": "Source",
						"value": "dbo.foods"
					},
					{
						"name": "Destination",
						"value": "dbo.foods"
					}
				],
				"typeProperties": {
					"source": {
						"type": "DelimitedTextSource",
						"storeSettings": {
							"type": "AzureBlobStorageReadSettings",
							"recursive": true
						},
						"formatSettings": {
							"type": "DelimitedTextReadSettings"
						}
					},
					"sink": {
						"type": "AzureSqlSink"
					},
					"enableStaging": false,
					"validateDataConsistency": false,
					"translator": {
						"type": "TabularTranslator",
						"mappings": [
							{
								"source": {
									"name": "Frequency",
									"type": "String",
									"physicalType": "varchar"
								},
								"sink": {
									"name": "frequency",
									"type": "String",
									"physicalType": "varchar"
								}
							},
							{
								"source": {
									"name": "Item",
									"type": "String",
									"physicalType": "varchar"
								},
								"sink": {
									"name": "item",
									"type": "String",
									"physicalType": "varchar"
								}
							},
							{
								"source": {
									"name": "Spend",
									"type": "Decimal",
									"physicalType": "float"
								},
								"sink": {
									"name": "spend",
									"type": "Decimal",
									"physicalType": "decimal"
								}
							},
							{
								"source": {
									"name": "FirstName",
									"type": "String",
									"physicalType": "varchar"
								},
								"sink": {
									"name": "firstname",
									"type": "String",
									"physicalType": "varchar"
								}
							},
							{
								"source": {
									"name": "Gender",
									"type": "String",
									"physicalType": "varchar"
								},
								"sink": {
									"name": "gender",
									"type": "String",
									"physicalType": "varchar"
								}
							},
							{
								"source": {
									"name": "City",
									"type": "String",
									"physicalType": "varchar"
								},
								"sink": {
									"name": "city",
									"type": "String",
									"physicalType": "varchar"
								}
							}
						],
						"typeConversion": true,
						"typeConversionSettings": {
							"allowDataTruncation": true,
							"treatBooleanAsNumber": false
						}
					}
				},
				"inputs": [
					{
						"referenceName": "Azureblobstorage_foods",
						"type": "DatasetReference"
					}
				],
				"outputs": [
					{
						"referenceName": "foodsdataset",
						"type": "DatasetReference"
					}
				]
			}
		],
		"annotations": []
	}
}